django_trashablemodels-1.0.1.dist-info/DESCRIPTION.rst
django_trashablemodels-1.0.1.dist-info/METADATA
django_trashablemodels-1.0.1.dist-info/RECORD
django_trashablemodels-1.0.1.dist-info/WHEEL
django_trashablemodels-1.0.1.dist-info/metadata.json
django_trashablemodels-1.0.1.dist-info/top_level.txt
trashable/__init__.py
trashable/admin.py
trashable/models.py
