Metadata-Version: 2.0
Name: django-trashablemodels
Version: 1.0.1
Summary: Implements a soft delete option for model instances
Home-page: https://github.com/vikingco/django-trashablemodels
Author: Unleashed NV
Author-email: operations@unleashed.be
License: MIT License
Platform: UNKNOWN
Classifier: Intended Audience :: Developers
Classifier: Programming Language :: Python
Classifier: Operating System :: OS Independent
Classifier: Environment :: Web Environment
Classifier: Framework :: Django
Requires-Dist: Django
